py_to_ts_interfaces/__init__.py
py_to_ts_interfaces/__main__.py
py_to_ts_interfaces/enums.py
py_to_ts_interfaces/file_io.py
py_to_ts_interfaces/interfaces.py
py_to_ts_interfaces/strings.py
py_to_ts_interfaces/type_converting.py
py_to_ts_interfaces/utils.py
py_to_ts_interfaces-1.4.0.dist-info/LICENSE
py_to_ts_interfaces-1.4.0.dist-info/METADATA
py_to_ts_interfaces-1.4.0.dist-info/WHEEL
py_to_ts_interfaces-1.4.0.dist-info/entry_points.txt
py_to_ts_interfaces-1.4.0.dist-info/top_level.txt
py_to_ts_interfaces-1.4.0.dist-info/RECORD
