Metadata-Version: 2.1
Name: py-to-ts-interfaces
Version: 1.4.0
Summary: A script to generate TypeScript interfaces from Python dataclasses, with enum support.
Home-page: https://github.com/Syndallic/py-to-ts-interfaces
Author: Peter Bell
Author-email: syndallic@outlook.com
Project-URL: Bug Tracker, https://github.com/Syndallic/py-to-ts-interfaces/issues
Classifier: Programming Language :: Python :: 3
Classifier: License :: OSI Approved :: MIT License
Classifier: Operating System :: OS Independent
Requires-Python: >=3.9
License-File: LICENSE
